pipremove/__init__.py
pipremove/pipremove.py
pipremove-0.0.7.dist-info/METADATA
pipremove-0.0.7.dist-info/WHEEL
pipremove-0.0.7.dist-info/entry_points.txt
pipremove-0.0.7.dist-info/RECORD
