Metadata-Version: 2.3
Name: pipremove
Version: 0.0.7
Summary: 删除模块包及其依赖包
Author-email: Li WeiJian <1330757852@qq.com>
Classifier: License :: OSI Approved :: MIT License
Classifier: Operating System :: OS Independent
Classifier: Programming Language :: Python :: 3
Requires-Python: >=3.7
Requires-Dist: pipdeptree
